<?xml version="1.0" encoding="UTF-8"?>
<!DOCTYPE mapper PUBLIC "-//mybatis.org//DTD Mapper 3.0//EN" "http://mybatis.org/dtd/mybatis-3-mapper.dtd">
<mapper namespace="com.demo.mapper.UserMapper">
  <resultMap id="BaseResultMap" type="com.demo.pojo.User">
    <!--
      WARNING - @mbg.generated
      This element is automatically generated by MyBatis Generator, do not modify.
      This element was generated on Fri Oct 09 13:21:39 CST 2020.
    -->
    <result column="USER" jdbcType="CHAR" property="USER" />
    <result column="CURRENT_CONNECTIONS" jdbcType="BIGINT" property="CURRENT_CONNECTIONS" />
    <result column="TOTAL_CONNECTIONS" jdbcType="BIGINT" property="TOTAL_CONNECTIONS" />
  </resultMap>
  <insert id="insert" parameterType="com.demo.pojo.User">
    <!--
      WARNING - @mbg.generated
      This element is automatically generated by MyBatis Generator, do not modify.
      This element was generated on Fri Oct 09 13:21:39 CST 2020.
    -->
    insert into users (USER, CURRENT_CONNECTIONS, TOTAL_CONNECTIONS
      )
    values (#{USER,jdbcType=CHAR}, #{CURRENT_CONNECTIONS,jdbcType=BIGINT}, #{TOTAL_CONNECTIONS,jdbcType=BIGINT}
      )
  </insert>
  <select id="selectAll" resultMap="BaseResultMap">
    <!--
      WARNING - @mbg.generated
      This element is automatically generated by MyBatis Generator, do not modify.
      This element was generated on Fri Oct 09 13:21:39 CST 2020.
    -->
    select USER, CURRENT_CONNECTIONS, TOTAL_CONNECTIONS
    from users
  </select>
</mapper>